[
    {
        "vin": "4T1B11HK5MU123456",
        "plate": "G37ABC",
        "state": "FL",
        "vehiculo": {
            "marca": "Toyota",
            "modelo": "Camry SE",
            "anio": 2021
        },
        "seguro": {
        "numero": "AIG-534433",
        "tipo": "Full Coverage" 
        },
        "especificaciones": {
            "VIN": "4T1B11HK5MU123456",
            "Marca": "Toyota",
            "Modelo": "Camry SE",
            "Color": "Metalizado Gris",
            "Año": "2021"
        },
        "historial": [
            "Alejandro Brito",
            "Address: 123 Main St, Anytown, USA",
            "Email: alejandro.brito@example.com",
            "Expiration Date: 30 de junio de 2023",
            "Purchase Date: 15 de marzo de 2020"
        ]
    },
    {
        "vin": "1HGCP2F8XBA000789",
        "plate": "JM1BPB",
        "state": "TX",
        "vehiculo": {
            "marca": "Honda",
            "modelo": "Civic EX",
            "anio": 2018
        },
        "seguro": {
        "numero": "AIG-554434",
        "tipo": "Full Coverage" 
        },
        "especificaciones": {
            "VIN": "1HGCP2F8XBA000789",
            "Marca": "Honda",
            "Modelo": "Civic EX",
            "Color": "Azul Cristal",
            "Año": "2018"
        },
        "historial": [
            "Alejandro Brito",
            "Address: 123 Main St, Anytown, USA",
            "Email: alejandro.brito@example.com",
            "Expiration Date: 30 de junio de 2023",
            "Purchase Date: 15 de marzo de 2020"
        ]
    },
    {
        "vin": "1HGCP2F8XBA000710",
        "plate": "JM2POP",
        "state": "CO",
        "vehiculo": {
            "marca": "FORD",
            "modelo": "Focus SE",
            "anio": 2018
        },
        "seguro": {
        "numero": "AIG-554477",
        "tipo": "Full Coverage" 
        },
        "especificaciones": {
            "VIN": "1HGCP2F8XBA000710",
            "Marca": "FORD",
            "Modelo": "Focus SE",
            "Color": "Verde Esmeralda",
            "Año": "2018"
        },
        "historial": [
            "Moises Carrero",
            "Address: 123 Main St, Anytown, USA",
            "Email: moises.carrero@example.com",
            "Purchase Date: 15 de marzo de 2020",
            "Expiration Date: 30 de junio de 2023"
        ]
    },
    {
        "vin": "2PHCP2F8XBA000710",
        "plate": "KP3POB",
        "state": "AL",
        "vehiculo": {
            "marca": "Chevrolet",
            "modelo": "Camaro SS",
            "anio": 2018
        },
        "seguro": {
        "numero": "AIG-553366",
        "tipo": "Full Coverage" 
        },
        "especificaciones": {
            "VIN": "2PHCP2F8XBA000710",
            "Marca": "Chevrolet",
            "Modelo": "Camaro SS",
            "Color": "Rojo Fuego",
            "Año": "2018"
        },
        "historial": [
            "David Ramirez",
            "Address: 123 Main St, Anytown, USA",
            "Email: david.ramirez@example.com",
            "Purchase Date: 22 de mayo de 2026",
            "Expiration Date: 22 de junio de 2026"
        ]
    },
    {
        "vin": "5UXFE83508L163385",
        "plate": "O15NJ8054",
        "state": "IL",
        "vehiculo": {
            "marca": "BMW",
            "modelo": "X5",
            "anio": 2008
        },
        "seguro": {
        "numero": "AIG-553366",
        "tipo": "Full Coverage"
        },
        "especificaciones": {
            "VIN": "5UXFE83508L163385",
            "Marca": "BMW",
            "Modelo": "X5",
            "Color": "Black",
            "Año": "2008"
        },
        "historial": [
            "Ramon Torres Jr",
            "Address: 5451 West Parker Ave",
            "Email: ldgafgordo1968@gmail.com",
            "Purchase Date: 27 de Mayo de 2026",
            "Expiration Date: 27 de Agosto de 2026"
        ]
    },
    {
        "vin": "1D7HU18N86J179930",
        "plate": "015NJ7890",
        "state": "IL",
        "vehiculo": {
            "marca": "Toyota",
            "modelo": "Camry SE",
            "anio": 2021
        },
        "seguro": {
        "numero": "AIG-534433",
        "tipo": "Full Coverage" 
        },
        "especificaciones": {
            "VIN": "1D7HU18N86J179930",
            "Marca": "Toyota",
            "Modelo": "Camry SE",
            "Color": "Metalizado Gris",
            "Año": "2021"
        },
        "historial": [
            "Felix Franco",
            "Address: 4714 S Marshfield ave Chicago IL",
            "Email: frafefranco377@gmail.com",
            "Expiration Date: 27 de Mayo de 2026",
            "Purchase Date: 27 de Agosto de 2026"
        ]
    }
]